formast
