Metadata-Version: 1.1
Name: formast
Version: 0.1.0a1
Summary: FormAST exposes file format descriptions through a simple API.
Home-page: https://github.com/amorilia/formast
Author: Amorilia
Author-email: amorilia@users.sourceforge.net
License: BSD
Download-URL: http://pypi.python.org/pypi/formast/
Keywords: file format,abstract syntax tree
Platform: any
Classifier: Development Status :: 3 - Alpha
Classifier: License :: OSI Approved :: BSD License
Classifier: Intended Audience :: Developers
Classifier: Topic :: Software Development :: Code Generators
Classifier: Topic :: Software Development :: Compilers
Classifier: Topic :: Software Development :: Interpreters
Classifier: Topic :: Text Processing :: Markup :: XML
Classifier: Programming Language :: C++
Classifier: Programming Language :: Python
Classifier: Programming Language :: Python :: 2
Classifier: Programming Language :: Python :: 2.6
Classifier: Programming Language :: Python :: 2.7
Classifier: Programming Language :: Python :: 3
Classifier: Programming Language :: Python :: 3.0
Classifier: Programming Language :: Python :: 3.1
Classifier: Programming Language :: Python :: 3.2
Classifier: Programming Language :: Python :: 3.3
Classifier: Operating System :: OS Independent
